gmcalc/__init__.py
gmcalc/heap_config.py
gmcalc/large_bins.py
gmcalc/main.py
gmcalc-0.0.1.dist-info/LICENSE
gmcalc-0.0.1.dist-info/METADATA
gmcalc-0.0.1.dist-info/WHEEL
gmcalc-0.0.1.dist-info/entry_points.txt
gmcalc-0.0.1.dist-info/top_level.txt
gmcalc-0.0.1.dist-info/RECORD
