Metadata-Version: 2.1
Name: gmcalc
Version: 0.0.1
Summary: Calculates glibc malloc chunk sizes of malloc and bins
Home-page: https://gitlab.com/Zer1t0/gmcalc
Author: Eloy Perez
Author-email: zer1t0ps@protonmail.com
License: UNKNOWN
Platform: UNKNOWN
Classifier: Programming Language :: Python :: 3
Classifier: License :: OSI Approved :: GNU General Public License v3 (GPLv3)
